package_version/__init__.py
package_version/package_version.py
package_version-1.0.5.dist-info/DESCRIPTION.rst
package_version-1.0.5.dist-info/METADATA
package_version-1.0.5.dist-info/RECORD
package_version-1.0.5.dist-info/WHEEL
package_version-1.0.5.dist-info/metadata.json
package_version-1.0.5.dist-info/pbr.json
package_version-1.0.5.dist-info/top_level.txt
tests/__init__.py
tests/test_package_version.py
